[{"model": "lessons.grade", "pk": 1, "fields": {"slug": "7-klass", "grade_year": "7 класс"}}, {"model": "lessons.grade", "pk": 2, "fields": {"slug": "8-klass", "grade_year": "8 класс"}}, {"model": "lessons.grade", "pk": 3, "fields": {"slug": "9-klass", "grade_year": "9 класс"}}, {"model": "lessons.grade", "pk": 4, "fields": {"slug": "10-klass", "grade_year": "10 класс"}}, {"model": "lessons.grade", "pk": 5, "fields": {"slug": "11-klass", "grade_year": "11 класс"}}, {"model": "lessons.grade", "pk": 6, "fields": {"slug": "12-klass", "grade_year": "12 класс"}}]